linkbiosite/__init__.py
linkbiosite/cli.py
linkbiosite/core.py
linkbiosite/data.py
linkbiosite/templates/base.html
linkbiosite/templates/index.html
linkbiosite/templates/styles.css
linkbiosite-3.0.0.dist-info/METADATA
linkbiosite-3.0.0.dist-info/WHEEL
linkbiosite-3.0.0.dist-info/entry_points.txt
linkbiosite-3.0.0.dist-info/top_level.txt
linkbiosite-3.0.0.dist-info/RECORD
