Metadata-Version: 2.4
Name: linkbiosite
Version: 3.0.0
Summary: A modern, brutalist-designed static site generator for link bio pages
Home-page: https://github.com/rafnixg/links
Author: Rafnix Guzmán
Author-email: Rafnix Guzmán <rafnixg@gmail.com>
Maintainer-email: Rafnix Guzmán <rafnixg@gmail.com>
License: MIT
Project-URL: Homepage, https://github.com/rafnixg/links
Project-URL: Documentation, https://linkbiosite.readthedocs.io/
Project-URL: Repository, https://github.com/rafnixg/links
Project-URL: Issues, https://github.com/rafnixg/links/issues
Project-URL: Changelog, https://github.com/rafnixg/links/blob/main/CHANGELOG.md
Keywords: static-site-generator,link-bio,jinja2,brutalist-design
Classifier: Development Status :: 4 - Beta
Classifier: Intended Audience :: Developers
Classifier: License :: OSI Approved :: MIT License
Classifier: Operating System :: OS Independent
Classifier: Programming Language :: Python :: 3
Classifier: Programming Language :: Python :: 3.8
Classifier: Programming Language :: Python :: 3.9
Classifier: Programming Language :: Python :: 3.10
Classifier: Programming Language :: Python :: 3.11
Classifier: Programming Language :: Python :: 3.12
Classifier: Topic :: Internet :: WWW/HTTP :: Site Management
Classifier: Topic :: Software Development :: Libraries :: Python Modules
Classifier: Topic :: Text Processing :: Markup :: HTML
Requires-Python: >=3.8
Requires-Dist: jinja2>=3.0.0
Provides-Extra: dev
Requires-Dist: pytest>=7.0.0; extra == "dev"
Requires-Dist: pytest-cov>=4.0.0; extra == "dev"
Requires-Dist: black>=22.0.0; extra == "dev"
Requires-Dist: isort>=5.10.0; extra == "dev"
Requires-Dist: flake8>=4.0.0; extra == "dev"
Requires-Dist: mypy>=1.0.0; extra == "dev"
Provides-Extra: docs
Requires-Dist: sphinx>=5.0.0; extra == "docs"
Requires-Dist: sphinx-rtd-theme>=1.2.0; extra == "docs"
Dynamic: author
Dynamic: home-page
Dynamic: requires-python
